setup.py
chat_server/__init__.py
chat_server/server_main.py
chat_server/common/__init__.py
chat_server/common/cpypt.py
chat_server/common/utils.py
chat_server/common/config/__init__.py
chat_server/common/config/codes.py
chat_server/common/config/methods.py
chat_server/common/config/system.py
chat_server/common/log/__init__.py
chat_server/common/log/client_log_config.py
chat_server/common/log/server_log_config.py
chat_server/docs/__init__.py
chat_server/docs/source/__init__.py
chat_server/docs/source/conf.py
chat_server/server/__init__.py
chat_server/server/register_new_user.py
chat_server/server/remove_user.py
chat_server/server/server_core.py
chat_server/server/server_database.py
chat_server/server/server_gui.py
chat_server/tests/__init__.py
chat_server/tests/test_server.py
chat_server/tests/test_utils.py
mess_chat_server_gb.egg-info/PKG-INFO
mess_chat_server_gb.egg-info/SOURCES.txt
mess_chat_server_gb.egg-info/dependency_links.txt
mess_chat_server_gb.egg-info/requires.txt
mess_chat_server_gb.egg-info/top_level.txt