Metadata-Version: 1.0
Name: mess-chat-server-gb
Version: 0.0.1
Summary: mess_chat_server_gb
Home-page: UNKNOWN
Author: Pavel Stefanenko
Author-email: p.stefanenko@gmail.com
License: UNKNOWN
Platform: UNKNOWN
